tjc_common/__init__.py
tjc_common-0.3.4.dist-info/LICENSE
tjc_common-0.3.4.dist-info/METADATA
tjc_common-0.3.4.dist-info/WHEEL
tjc_common-0.3.4.dist-info/top_level.txt
tjc_common-0.3.4.dist-info/RECORD
